Workbook

Sheet 機能一覧
A1: 業務分類 | B1: 番号 | C1: 機能ID | D1: ScreenID | E1: 機能名称 | F1: 内容
A2: 画面 | B2: 1 | C2: FPPR0010AC | D2: SCR-SAMPLE-001 | E2: Sample Function 1 | F2: COOOLaで入力された入荷実績の確認・訂正を行う。 検収実績の確認、差戻の登録を行う。
B3: 2 | C3: FPMT10391 | D3: SCR-SAMPLE-002 | E3: Sample Function 2 | F3: ・仕入データより、買掛データの作成を行う。 ・消費税の計上を行う。
B4: 3 | C4: FPPR00501AC | D4: SCR-SAMPLE-003 | E4: Sample Function 3 | F4: ・支払通知書を作成したデータを対象に、仕入先に対する承認依頼の登録を行う。 ・請求書管理を行う仕入先の請求書受領状況の登録を行う。
B5: 4 | C5: FPVM10131 | D5: SCR-SAMPLE-004 | E5: Sample Function 4 | F5: 買掛データより、支払通知書の出力を行う。 ①支払通知書 ②支払明細書
B6: 5 | C6: FPPR00901AC | D6: SCR-SAMPLE-005 | E6: Sample Function 5 | F6: ANACより支払通知書承認依頼されたデータを対象に、支払通知書の承認を行う。 差戻の場合は、差戻理由の登録を行う。
B7: 6 | C7: FPPR00201AC | D7: SCR-SAMPLE-006 | E7: Sample Function 6 | F7: 買掛データより、仕入計上のCSV出力を行う・
B8: 7 | C8: FPPR00601AC | D8: SCR-SAMPLE-007 | E8: Sample Function 7 | F8: 各種CSVの出力を行う。 ①単価不一致確認表情報 ②検収実績情報 ③入庫実績情報 ④アイテム別年間仕入一覧 ⑤サプライヤー別購入金額一覧

Sheet Milestone
A2: 機能改善フェーズ | D2: March | H2: April | L2: May | P2: Jun | T2: July
D3: 1W | E3: 2W | F3: 3W | G3: 4W | H3: 1W | I3: 2W | J3: 3W | K3: 4W | L3: 1W | M3: 2W | N3: 3W | O3: 4W | P3: 1W | Q3: 2W | R3: 3W | S3: 4W | T3: 1W | U3: 2W | V3: 3W | W3: 4W
A4: 環境設定
A5: システム理解やQAやり取り
A6: 実装
A7: 単体テスト仕様作成
A8: 単体テスト

Sheet 工数詳細
G1: 開発の | H1: 開発の | I1: 開発の | J1: 開発の | K1: 単体テスト仕様書の | L1: 開発の | M1: 開発の | N1: 開発の | O1: 開発～単体の | P1: 開発～単体の
G2: 0.1 | H2: 0.1 | I2: 0.05 | J2: 0.3 | K2: 0.15 | L2: 0.3 | M2: 0.1 | N2: 0.02 | O2: 0.03 | P2: 0.05
H3: 仕様理解 | J3: 単体テスト
A4: 業務分類 | B4: 番号 | C4: 機能ID | D4: 機能名称 | E4: Status | F4: 実装工数 (h) | G4: コードレビュー (h) | H4: 仕様理解 (h) | I4: QA (h) | J4: テスト仕様書 (h) | K4: レビュー (h) | L4: 実施 (h) | M4: テストデータ作成 (h) | N4: 付帯作業 (h) | O4: リスク (h) | P4: 管理工数 (h) | Q4: 合計 (h)
A5: Sample Category | B5: 1 | C5: SCR-SAMPLE-001 | D5: =VLOOKUP(C5,機能一覧!$D$2:$F$8,2,FALSE) | E5: 中 | F5: 40 | G5: =F5*G$2 | H5: =F5*H$2 | I5: =$F5*I$2 | J5: =F5*J$2 | K5: =J5*K$2 | L5: =F5*L$2 | M5: =F5*M$2 | N5: =F5*N$2 | O5: =(F5+H5+J5+L5)*O$2 | P5: =SUM(F5:M5)*P$2 | Q5: =SUM(F5:P5)
B6: 2 | C6: SCR-SAMPLE-002 | D6: =VLOOKUP(C6,機能一覧!$D$2:$F$8,2,FALSE) | E6: 大 | F6: 30 | G6: =F6*G$2 | H6: =F6*H$2 | I6: =$F6*I$2 | J6: =F6*J$2 | K6: =J6*K$2 | L6: =F6*L$2 | M6: =F6*M$2 | N6: =F6*N$2 | O6: =(F6+H6+J6+L6)*O$2 | P6: =SUM(F6:M6)*P$2 | Q6: =SUM(F6:P6)
B7: 3 | C7: SCR-SAMPLE-003 | D7: =VLOOKUP(C7,機能一覧!$D$2:$F$8,2,FALSE) | E7: 小 | F7: 50 | G7: =F7*G$2 | H7: =F7*H$2 | I7: =$F7*I$2 | J7: =F7*J$2 | K7: =J7*K$2 | L7: =F7*L$2 | M7: =F7*M$2 | N7: =F7*N$2 | O7: =(F7+H7+J7+L7)*O$2 | P7: =SUM(F7:M7)*P$2 | Q7: =SUM(F7:P7)
B8: 4 | C8: SCR-SAMPLE-004 | D8: =VLOOKUP(C8,機能一覧!$D$2:$F$8,2,FALSE) | E8: 中 | F8: 40 | G8: =F8*G$2 | H8: =F8*H$2 | I8: =$F8*I$2 | J8: =F8*J$2 | K8: =J8*K$2 | L8: =F8*L$2 | M8: =F8*M$2 | N8: =F8*N$2 | O8: =(F8+H8+J8+L8)*O$2 | P8: =SUM(F8:M8)*P$2 | Q8: =SUM(F8:P8)
B9: 5 | C9: SCR-SAMPLE-005 | D9: =VLOOKUP(C9,機能一覧!$D$2:$F$8,2,FALSE) | E9: 小 | F9: 30 | G9: =F9*G$2 | H9: =F9*H$2 | I9: =$F9*I$2 | J9: =F9*J$2 | K9: =J9*K$2 | L9: =F9*L$2 | M9: =F9*M$2 | N9: =F9*N$2 | O9: =(F9+H9+J9+L9)*O$2 | P9: =SUM(F9:M9)*P$2 | Q9: =SUM(F9:P9)
B10: 6 | C10: SCR-SAMPLE-006 | D10: =VLOOKUP(C10,機能一覧!$D$2:$F$8,2,FALSE) | E10: 中 | F10: 40 | G10: =F10*G$2 | H10: =F10*H$2 | I10: =$F10*I$2 | J10: =F10*J$2 | K10: =J10*K$2 | L10: =F10*L$2 | M10: =F10*M$2 | N10: =F10*N$2 | O10: =(F10+H10+J10+L10)*O$2 | P10: =SUM(F10:M10)*P$2 | Q10: =SUM(F10:P10)
B11: 7 | C11: SCR-SAMPLE-007 | D11: =VLOOKUP(C11,機能一覧!$D$2:$F$8,2,FALSE) | E11: 小 | F11: 30 | G11: =F11*G$2 | H11: =F11*H$2 | I11: =$F11*I$2 | J11: =F11*J$2 | K11: =J11*K$2 | L11: =F11*L$2 | M11: =F11*M$2 | N11: =F11*N$2 | O11: =(F11+H11+J11+L11)*O$2 | P11: =SUM(F11:M11)*P$2 | Q11: =SUM(F11:P11)
C12: 1人(h) | F12: =SUM(F5:F11) | G12: =SUM(G5:G11) | H12: =SUM(H5:H11) | I12: =SUM(I5:I11) | J12: =SUM(J5:J11) | K12: =SUM(K5:K11) | L12: =SUM(L5:L11) | M12: =SUM(M5:M11) | ... Q12: =SUM(Q5:Q11)
C13: 1人(日) | F13: =F12/8 | G13: =G12/8 | H13: =H12/8 | I13: =I12/8 | J13: =J12/8 | K13: =K12/8 | L13: =L12/8 | M13: =M12/8 | ... Q13: =Q12/8
C14: 1人(月) | F14: =F13/20 | G14: =G13/20 | H14: =H13/20 | I14: =I13/20 | J14: =J13/20 | K14: =K13/20 | L14: =L13/20 | M14: =M13/20 | ... Q14: =Q13/20
C15: ="Leader " &D$20& "人+ Developer "&D$21&"人 (h)" | F15: =F12/$D21 | G15: =G12/$D20 | H15: =H12/$D20 | I15: =I12/$D20 | J15: =J12/$D21 | K15: =K12/$D20 | L15: =L12/$D21 | M15: =M12/$D21 | N15: =N12/$D21 | O15: =O12/$D21 | P15: =P12/$D20 | Q15: =SUM(F15:P15) | R15: 人時
C16: ="Leader " &D$20& "人+ Developer "&D$21&"人 (h)" | F16: =F15/8 | G16: =G15/8 | H16: =H15/8 | I16: =I15/8 | J16: =J15/8 | K16: =K15/8 | L16: =L15/8 | M16: =M15/8 | ... Q16: =Q15/8 | R16: 人日
C17: ="Leader " &D$20& "人+ Developer "&D$21&"人 (h)" | F17: =F16/20 | G17: =G16/20 | H17: =H16/20 | I17: =I16/20 | J17: =J16/20 | K17: =K16/20 | L17: =L16/20 | M17: =M16/20 | ... Q17: =Q16/20 | R17: 人月
C19: 体制
C20: Leader | D20: 1
C21: Developer | D21: 4

Sheet 工数・費用
A1: 工数・費用
B3: ブライセン（ミャンマー）
B4: メンバー | C4: 役割 | D4: 等級 | E4: 2026/03 | H4: 2026/04 | K4: 2026/05 | N4: 合計
E5: 工数(人月) | F5: 単価(円) | G5: 合計金額(円) | H5: 工数(人月) | I5: 単価(円) | J5: 合計金額(円) | K5: 工数(人月) | L5: 単価(円) | M5: 合計金額(円) | N5: 工数(人月) | O5: 合計金額(円)
B6: MINTZU HNIN KHAT ※プロジェクトの監視・週次チェック | C6: マネージャー | E6: 0.2 | G6: =E6*F6 | H6: 0.2 | J6: =H6*I6 | M6: =K6*L6 | N6: =SUMIF($E$5:$M$5,N$5,$E6:$M6) | O6: =SUMIF($E$5:$M$5,O$5,$E6:$M6)
B7: HNIN SU HLAING | C7: リーダー | E7: 1 | G7: =E7*F7 | H7: 0.25 | J7: =H7*I7 | M7: =K7*L7 | N7: =SUMIF($E$5:$M$5,N$5,$E7:$M7) | O7: =SUMIF($E$5:$M$5,O$5,$E7:$M7)
B8: KAUNG HTET SAN | C8: エンジニア | E8: 1 | G8: =E8*F8 | H8: 0.25 | J8: =H8*I8 | M8: =K8*L8 | N8: =SUMIF($E$5:$M$5,N$5,$E8:$M8) | O8: =SUMIF($E$5:$M$5,O$5,$E8:$M8)
B9: YOON MYAT CHERRY OO | C9: エンジニア | E9: 1 | G9: =E9*F9 | H9: 0.25 | J9: =H9*I9 | M9: =K9*L9 | N9: =SUMIF($E$5:$M$5,N$5,$E9:$M9) | O9: =SUMIF($E$5:$M$5,O$5,$E9:$M9)
B10: AUNG PYAE SONE HTUN | C10: エンジニア | E10: 1 | G10: =E10*F10 | H10: 0.25 | J10: =H10*I10 | M10: =K10*L10 | N10: =SUMIF($E$5:$M$5,N$5,$E10:$M10) | O10: =SUMIF($E$5:$M$5,O$5,$E10:$M10)
N11: =SUMIF($E$5:$M$5,N$5,$E11:$M11) | O11: =SUMIF($E$5:$M$5,O$5,$E11:$M11)
B12: 合計 | E12: =SUM(E6:E11) | F12: - | G12: =SUM(G6:G11) | H12: =SUM(H6:H11) | I12: - | J12: =SUM(J6:J11) | K12: =SUM(K6:K11) | L12: - | M12: =SUM(M6:M11) | N12: =SUM(N6:N11) | O12: =SUM(O6:O11)
B14: ブライセン（カンボジア）
B15: メンバー | C15: 役割 | D15: 等級 | E15: 2026/03 | H15: 2026/04 | K15: 2026/05 | N15: 合計
E16: 工数(人月) | F16: 単価(円) | G16: 合計金額(円) | H16: 工数(人月) | I16: 単価(円) | J16: 合計金額(円) | K16: 工数(人月) | L16: 単価(円) | M16: 合計金額(円) | N16: 工数(人月) | O16: 合計金額(円)
B17: PHYO NAING HTUN | C17: エンジニア | E17: 1 | G17: =E17*F17 | H17: 0.25 | J17: =H17*I17 | M17: =K17*L17 | N17: =SUMIF($E$16:$M$16,N$16,$E17:$M17) | O17: =SUMIF($E$16:$M$16,O$16,$E17:$M17)
N18: =SUMIF($E$16:$M$16,N$16,$E18:$M18) | O18: =SUMIF($E$16:$M$16,O$16,$E18:$M18)
B19: 合計 | E19: =SUM(E17:E18) | F19: - | G19: =SUM(G17:G18) | H19: =SUM(H17:H18) | I19: - | J19: =SUM(J17:J18) | K19: =SUM(K17:K18) | L19: - | M19: =SUM(M17:M18) | N19: =SUM(N17:N18) | O19: =SUM(O17:O18)
